flipside/__init__.py
flipside/flipside.py
flipside/rpc.py
flipside/shroomdk.py
flipside/errors/__init__.py
flipside/errors/api_error.py
flipside/errors/base_error.py
flipside/errors/query_run_errors.py
flipside/errors/sdk_error.py
flipside/errors/server_error.py
flipside/integrations/__init__.py
flipside/integrations/query_integration/__init__.py
flipside/integrations/query_integration/compass_query_integration.py
flipside/integrations/query_integration/defaults.py
flipside/integrations/query_integration/query_result_set_builder.py
flipside/models/__init__.py
flipside/models/query.py
flipside/models/query_defaults.py
flipside/models/query_result_set.py
flipside/models/query_run_stats.py
flipside/models/query_status.py
flipside/models/sleep_config.py
flipside/models/compass/__init__.py
flipside/models/compass/cancel_query_run.py
flipside/models/compass/create_query_run.py
flipside/models/compass/get_query_run.py
flipside/models/compass/get_query_run_results.py
flipside/models/compass/get_sql_statement.py
flipside/models/compass/query_results.py
flipside/models/compass/core/__init__.py
flipside/models/compass/core/column_metadata.py
flipside/models/compass/core/page.py
flipside/models/compass/core/page_stats.py
flipside/models/compass/core/query_request.py
flipside/models/compass/core/query_run.py
flipside/models/compass/core/result_format.py
flipside/models/compass/core/rpc_error.py
flipside/models/compass/core/rpc_request.py
flipside/models/compass/core/rpc_response.py
flipside/models/compass/core/sql_statement.py
flipside/models/compass/core/tags.py
flipside/tests/__init__.py
flipside/tests/test_rpc.py
flipside/tests/integrations/__init__.py
flipside/tests/integrations/query_integration/__init__.py
flipside/tests/integrations/query_integration/test_query_compass_integration.py
flipside/tests/integrations/query_integration/test_query_result_set_builder.py
flipside/tests/models/__init__.py
flipside/tests/models/test_query_status.py
flipside/tests/utils/__init__.py
flipside-2.1.0.dist-info/LICENSE.txt
flipside-2.1.0.dist-info/METADATA
flipside-2.1.0.dist-info/WHEEL
flipside-2.1.0.dist-info/top_level.txt
flipside-2.1.0.dist-info/RECORD
